dubbo/__init__.py
dubbo/client.py
dubbo/codec/__init__.py
dubbo/codec/decoder.py
dubbo/codec/encoder.py
dubbo/common/__init__.py
dubbo/common/constants.py
dubbo/common/exceptions.py
dubbo/common/loggers.py
dubbo/common/util.py
dubbo/connection/__init__.py
dubbo/connection/connections.py
ke_python_dubbo-1.0.0.dist-info/licenses/LICENSE
ke_python_dubbo-1.0.0.dist-info/METADATA
ke_python_dubbo-1.0.0.dist-info/WHEEL
ke_python_dubbo-1.0.0.dist-info/top_level.txt
ke_python_dubbo-1.0.0.dist-info/RECORD
