Metadata-Version: 2.4
Name: ke-python-dubbo
Version: 1.0.0
Summary: Python Dubbo Client.
Home-page: https://github.com/cnzhangjianguo/python-dubbo
Author: cn.zhangjianguo
Author-email: cn.zhangjianguo@gmail.com
License: Apache License 2.0
Classifier: Environment :: Console
Classifier: Intended Audience :: Developers
Classifier: Natural Language :: Chinese (Simplified)
Classifier: Operating System :: OS Independent
Classifier: Programming Language :: Python :: 3.13
License-File: LICENSE
Requires-Dist: kazoo==2.8.0
Dynamic: author
Dynamic: author-email
Dynamic: classifier
Dynamic: home-page
Dynamic: license
Dynamic: license-file
Dynamic: requires-dist
Dynamic: summary
